nahual/process.py
nahual/readme.md
nahual/serial.py
nahual/server.py
nahual/transport.py
nahual/visualise.py
nahual/client/baby.py
nahual-0.0.5.dist-info/METADATA
nahual-0.0.5.dist-info/WHEEL
nahual-0.0.5.dist-info/RECORD
