Metadata-Version: 2.4
Name: nahual
Version: 0.0.5
Summary: Deploy and access image and data processing models across processes.
Project-URL: Homepage, https://github.com/broadinstitute/monorepo/tree/main/libs/jump_babel
Author: Alan Munoz
Requires-Python: <=3.13,>=3.9
Requires-Dist: numpy<3
Requires-Dist: pynng>=0.8.1
Requires-Dist: requests
